bhammer/__init__.py
bhammer/__main__.py
bhammer-1.1.dist-info/LICENSE
bhammer-1.1.dist-info/METADATA
bhammer-1.1.dist-info/WHEEL
bhammer-1.1.dist-info/entry_points.txt
bhammer-1.1.dist-info/top_level.txt
bhammer-1.1.dist-info/RECORD
